vivid_2024/__init__.py
vivid_2024/main.py
vivid_2024-0.1.1.dist-info/LICENSE
vivid_2024-0.1.1.dist-info/METADATA
vivid_2024-0.1.1.dist-info/WHEEL
vivid_2024-0.1.1.dist-info/top_level.txt
vivid_2024-0.1.1.dist-info/RECORD
