Metadata-Version: 2.1
Name: vivid-2024
Version: 0.1.1
Summary: A comprehensive platform for HR professionals.
Home-page: https://github.com/arnabc-hub/vivid
Author: Your Name
Author-email: your.email@example.com
Classifier: Programming Language :: Python :: 3
Classifier: License :: OSI Approved :: MIT License
Classifier: Operating System :: OS Independent
Requires-Python: >=3.6
License-File: LICENSE
